easy_video/__init__.py
easy_video/open_type.py
easy_video/video.py
easy_video-0.0.4.dist-info/LICENSE
easy_video-0.0.4.dist-info/METADATA
easy_video-0.0.4.dist-info/WHEEL
easy_video-0.0.4.dist-info/top_level.txt
easy_video-0.0.4.dist-info/RECORD
