Metadata-Version: 2.1
Name: easy-video
Version: 0.0.4
Summary: Wrap OpenCV package for make accessing video-file easier.
Home-page: https://github.com/MTamon/VideoTools.git
Author: Tamon Mikawa
Author-email: mtamon.engineering@gmail.com
License: MIT License
Keywords: opencv,wrapper,video I/O,video processing
Classifier: Development Status :: 4 - Beta
Classifier: License :: OSI Approved :: MIT License
Classifier: Programming Language :: Python
Classifier: Programming Language :: Python :: 3
Classifier: Programming Language :: Python :: 3.9
Classifier: Topic :: Software Development :: Libraries :: Python Modules
License-File: LICENSE
Requires-Dist: moviepy
Requires-Dist: numpy
Requires-Dist: opencv-contrib-python
Requires-Dist: opencv-python
